pandeia/__init__.py
pandeia/engine/LICENSE.rst
pandeia/engine/__init__.py
pandeia/engine/astro_spectrum.py
pandeia/engine/background.py
pandeia/engine/bnc.py
pandeia/engine/calc_utils.py
pandeia/engine/config.py
pandeia/engine/constants.py
pandeia/engine/coords.py
pandeia/engine/custom_exceptions.py
pandeia/engine/data_util.py
pandeia/engine/debug_utils.py
pandeia/engine/detector.py
pandeia/engine/detector_factory.py
pandeia/engine/etc3D.py
pandeia/engine/exposure.py
pandeia/engine/exposure_factory.py
pandeia/engine/extinction.py
pandeia/engine/hst.py
pandeia/engine/instrument.py
pandeia/engine/instrument_factory.py
pandeia/engine/io_utils.py
pandeia/engine/jwst.py
pandeia/engine/noise.py
pandeia/engine/normalization.py
pandeia/engine/observation.py
pandeia/engine/pandeia_warnings.py
pandeia/engine/perform_calculation.py
pandeia/engine/profile.py
pandeia/engine/projection.py
pandeia/engine/psf_library.py
pandeia/engine/report.py
pandeia/engine/roman.py
pandeia/engine/scene.py
pandeia/engine/sed.py
pandeia/engine/signal.py
pandeia/engine/source.py
pandeia/engine/strategy.py
pandeia/engine/telescope.py
pandeia/engine/utils.py
pandeia/engine/defaults/__init__.py
pandeia/engine/defaults/background_defaults.json
pandeia/engine/defaults/calculationconfig_defaults.json
pandeia/engine/defaults/insconfig_defaults.json
pandeia/engine/defaults/observation_defaults.json
pandeia/engine/helpers/DEVBUILD
pandeia/engine/helpers/README.md
pandeia/engine/helpers/__init__.py
pandeia/engine/helpers/background/__init__.py
pandeia/engine/helpers/background/butler.py
pandeia/engine/helpers/background/hst/__init__.py
pandeia/engine/helpers/background/hst/sky.dat
pandeia/engine/helpers/background/hst/sky.py
pandeia/engine/helpers/background/hst/sky_angles.py
pandeia/engine/helpers/background/hst/sky_spectrum.py
pandeia/engine/helpers/background/hst/util.py
pandeia/engine/helpers/background/hst/zodi.dat
pandeia/engine/helpers/background/jwst/__init__.py
pandeia_engine-2026.1.dist-info/METADATA
pandeia_engine-2026.1.dist-info/WHEEL
pandeia_engine-2026.1.dist-info/top_level.txt
pandeia_engine-2026.1.dist-info/RECORD
