Metadata-Version: 2.4
Name: pandeia.engine
Version: 2026.1
Summary: Pandeia 3D Exposure Time Calculator compute engine
Home-page: https://jwst.etc.stsci.edu
Author: Adric Riedel, Isaac Spitzer, Dharini Chittiraibalan, Chris Sontag, Oi In Tam, Ivo Busko, Craig Jones, Tim Pickering, Klaus Pontoppidan
Classifier: Intended Audience :: Science/Research
Classifier: License :: OSI Approved :: BSD License
Classifier: Operating System :: OS Independent
Classifier: Programming Language :: Python :: 3
Classifier: Programming Language :: Python :: 3.9
Classifier: Programming Language :: Python :: 3.10
Classifier: Programming Language :: Python :: 3.11
Classifier: Programming Language :: Python :: 3.12
Classifier: Topic :: Scientific/Engineering :: Astronomy
Classifier: Topic :: Software Development :: Libraries :: Python Modules
Requires-Dist: numpy>=1.21
Requires-Dist: scipy>=1.9.2
Requires-Dist: astropy>=5.3
Requires-Dist: photutils
Requires-Dist: synphot
Requires-Dist: stsynphot
Requires-Dist: setuptools
Dynamic: author
Dynamic: classifier
Dynamic: description
Dynamic: home-page
Dynamic: requires-dist
Dynamic: summary
